{
    "name": "Cow Girl, Squire |+ Unhand",
    "modpack": "Ceo",
    "length": 2,
    "destination": "vanilla_MIy9!KFy6_Ho_KfCowG",
    "speeds": [
        {
            "animation": "osex_vanilla_KfCowGHJO+10CX"
        }
    ],
    "actors": [
        {
            "intendedSex": "male",
            "sosBend": 0,
            "scale": 1.03,
            "tags": [
                "lyingback"
            ],
            "feetOnGround": false
        },
        {
            "intendedSex": "female",
            "tags": [
                "kneeling"
            ],
            "feetOnGround": true
        }
    ],
    "actions": [
        {
            "type": "handjob",
            "actor": 1,
            "target": 0
        }
    ],
    "tags": [
        "osa"
    ]
}